{
    "title": "Lovells",
    "about": "This is a sample site generated by a SPARQL query for people with the last name Lovell.",
    "sparql": "SELECT DISTINCT ?item ?itemLabel WHERE {\n  SERVICE wikibase:label { bd:serviceParam wikibase:language \"[AUTO_LANGUAGE]\". }\n  {\n    SELECT DISTINCT ?item WHERE {\n      ?item p:P734 ?statement0.\n      ?statement0 (ps:P734/(wdt:P279*)) wd:Q16872538.\n      ?item p:P18 ?statement1.\n      ?statement1 (ps:P18) _:anyValueP18.\n    }\n    LIMIT 100\n  }\n}",
    "idList": ["Q18575825"],
    "copyright": "Yale University"
}